code_ast/__init__.py
code_ast/ast.py
code_ast/config.py
code_ast/parsers.py
code_ast/transformer.py
code_ast/visitor.py
code_ast-0.1.2.dist-info/licenses/LICENSE
code_ast-0.1.2.dist-info/METADATA
code_ast-0.1.2.dist-info/WHEEL
code_ast-0.1.2.dist-info/top_level.txt
code_ast-0.1.2.dist-info/RECORD
