Metadata-Version: 2.4
Name: code_ast
Version: 0.1.2
Summary: Fast structural analysis of any programming language in Python
Home-page: https://github.com/cedricrupb/code_ast
Download-URL: https://github.com/cedricrupb/code_ast/archive/refs/tags/v0.1.0.tar.gz
Author: Cedric Richter
Author-email: Cedric Richter <cedricr.upb@gmail.com>
Maintainer-email: Cedric Richter <cedricr.upb@gmail.com>
License-Expression: MIT
Project-URL: Homepage, https://github.com/cedricrupb/code_ast
Project-URL: Bug Reports, https://github.com/cedricrupb/code_ast/issues
Project-URL: Source, https://github.com/cedricrupb/code_ast
Keywords: code,ast,cst,syntax,program,language processing
Classifier: Development Status :: 3 - Alpha
Classifier: Intended Audience :: Developers
Classifier: Topic :: Software Development :: Build Tools
Classifier: Programming Language :: Python :: 3
Classifier: Programming Language :: Python :: 3.6
Classifier: Programming Language :: Python :: 3.7
Classifier: Programming Language :: Python :: 3.8
Classifier: Programming Language :: Python :: 3.9
Classifier: Programming Language :: Python :: 3.10
Classifier: Programming Language :: Python :: 3.11
Classifier: Programming Language :: Python :: 3.12
Classifier: Programming Language :: Python :: 3.13
Classifier: Programming Language :: Python :: 3 :: Only
Requires-Python: >=3.8
License-File: LICENSE
Requires-Dist: tree_sitter
Requires-Dist: GitPython
Requires-Dist: requests
Dynamic: author
Dynamic: download-url
Dynamic: home-page
Dynamic: license-file
